<?xml version="1.0" encoding="UTF-8"?>
<GenRun Id="impl_1" LaunchPart="xczu9eg-ffvb1156-2-e" LaunchTime="1752910699">
  <File Type="ROUTE-PWR" Name="Shrinking_Layer_power_routed.rpt"/>
  <File Type="PA-TCL" Name="Shrinking_Layer.tcl"/>
  <File Type="ROUTE-PWR-SUM" Name="Shrinking_Layer_power_summary_routed.pb"/>
  <File Type="REPORTS-TCL" Name="Shrinking_Layer_reports.tcl"/>
  <File Type="BITSTR-MSK" Name="Shrinking_Layer.msk"/>
  <File Type="ROUTE-CLK" Name="Shrinking_Layer_clock_utilization_routed.rpt"/>
  <File Type="RDI-RDI" Name="Shrinking_Layer.vdi"/>
  <File Type="POSTROUTE-PHYSOPT-BUS-SKEW-PB" Name="Shrinking_Layer_bus_skew_postroute_physopted.pb"/>
  <File Type="BG-BIT" Name="Shrinking_Layer.bit"/>
  <File Type="BG-DRC" Name="Shrinking_Layer.drc"/>
  <File Type="BG-BGN" Name="Shrinking_Layer.bgn"/>
  <File Type="BG-BIN" Name="Shrinking_Layer.bin"/>
  <File Type="BITSTR-RBT" Name="Shrinking_Layer.rbt"/>
  <File Type="BITSTR-NKY" Name="Shrinking_Layer.nky"/>
  <File Type="BITSTR-BMM" Name="Shrinking_Layer_bd.bmm"/>
  <File Type="BITSTR-MMI" Name="Shrinking_Layer.mmi"/>
  <File Type="ROUTE-METHODOLOGY-DRC" Name="Shrinking_Layer_methodology_drc_routed.rpt"/>
  <File Type="BITSTR-SYSDEF" Name="Shrinking_Layer.sysdef"/>
  <File Type="ROUTE-METHODOLOGY-DRC-PB" Name="Shrinking_Layer_methodology_drc_routed.pb"/>
  <File Type="BITSTR-LTX" Name="debug_nets.ltx"/>
  <File Type="BITSTR-LTX" Name="Shrinking_Layer.ltx"/>
  <File Type="BOOT-PDI-FILE" Name="Shrinking_Layer_soc.pdi"/>
  <File Type="WBT-USG" Name="usage_statistics_webtalk.html"/>
  <File Type="NPI_FILE" Name="Shrinking_Layer.npi"/>
  <File Type="OPT-DRC" Name="Shrinking_Layer_drc_opted.rpt"/>
  <File Type="RBD_FILE" Name="Shrinking_Layer.rbd"/>
  <File Type="OPT-HWDEF" Name="Shrinking_Layer.hwdef"/>
  <File Type="PLACE-IO" Name="Shrinking_Layer_io_placed.rpt"/>
  <File Type="PLACE-UTIL" Name="Shrinking_Layer_utilization_placed.rpt"/>
  <File Type="PLACE-UTIL-PB" Name="Shrinking_Layer_utilization_placed.pb"/>
  <File Type="PLACE-CTRL" Name="Shrinking_Layer_control_sets_placed.rpt"/>
  <File Type="PLACE-PRE-SIMILARITY" Name="Shrinking_Layer_incremental_reuse_pre_placed.rpt"/>
  <File Type="ROUTE-DRC" Name="Shrinking_Layer_drc_routed.rpt"/>
  <File Type="ROUTE-DRC-PB" Name="Shrinking_Layer_drc_routed.pb"/>
  <File Type="ROUTE-PWR-RPX" Name="Shrinking_Layer_power_routed.rpx"/>
  <File Type="ROUTE-STATUS" Name="Shrinking_Layer_route_status.rpt"/>
  <File Type="ROUTE-STATUS-PB" Name="Shrinking_Layer_route_status.pb"/>
  <File Type="ROUTE-DCP" Name="Shrinking_Layer_routed.dcp"/>
  <File Type="ROUTE-ERROR-DCP" Name="Shrinking_Layer_routed_error.dcp"/>
  <File Type="ROUTE-BLACKBOX-DCP" Name="Shrinking_Layer_routed_bb.dcp"/>
  <File Type="ROUTE-TIMINGSUMMARY" Name="Shrinking_Layer_timing_summary_routed.rpt"/>
  <File Type="ROUTE-TIMING-PB" Name="Shrinking_Layer_timing_summary_routed.pb"/>
  <File Type="ROUTE-TIMING-RPX" Name="Shrinking_Layer_timing_summary_routed.rpx"/>
  <File Type="ROUTE-SIMILARITY" Name="Shrinking_Layer_incremental_reuse_routed.rpt"/>
  <File Type="ROUTE-BUS-SKEW" Name="Shrinking_Layer_bus_skew_routed.rpt"/>
  <File Type="ROUTE-BUS-SKEW-PB" Name="Shrinking_Layer_bus_skew_routed.pb"/>
  <File Type="ROUTE-BUS-SKEW-RPX" Name="Shrinking_Layer_bus_skew_routed.rpx"/>
  <File Type="OPT-DCP" Name="Shrinking_Layer_opt.dcp"/>
  <File Type="PLACE-DCP" Name="Shrinking_Layer_placed.dcp"/>
  <File Type="PWROPT-DCP" Name="Shrinking_Layer_pwropt.dcp"/>
  <File Type="POSTPLACE-PWROPT-DCP" Name="Shrinking_Layer_postplace_pwropt.dcp"/>
  <File Type="PHYSOPT-DCP" Name="Shrinking_Layer_physopt.dcp"/>
  <File Type="POSTROUTE-PHYSOPT-DCP" Name="Shrinking_Layer_postroute_physopt.dcp"/>
  <File Type="POSTROUTE-PHYSOPT-BLACKBOX-DCP" Name="Shrinking_Layer_postroute_physopt_bb.dcp"/>
  <File Type="POSTROUTE-PHYSOPT-TIMING" Name="Shrinking_Layer_timing_summary_postroute_physopted.rpt"/>
  <File Type="POSTROUTE-PHYSOPT-TIMING-PB" Name="Shrinking_Layer_timing_summary_postroute_physopted.pb"/>
  <File Type="POSTROUTE-PHYSOPT-TIMING-RPX" Name="Shrinking_Layer_timing_summary_postroute_physopted.rpx"/>
  <File Type="POSTROUTE-PHYSOPT-BUS-SKEW" Name="Shrinking_Layer_bus_skew_postroute_physopted.rpt"/>
  <File Type="POSTROUTE-PHYSOPT-BUS-SKEW-RPX" Name="Shrinking_Layer_bus_skew_postroute_physopted.rpx"/>
  <File Type="ROUTE-DRC-RPX" Name="Shrinking_Layer_drc_routed.rpx"/>
  <File Type="ROUTE-METHODOLOGY-DRC-RPX" Name="Shrinking_Layer_methodology_drc_routed.rpx"/>
  <File Type="PDI-FILE" Name="Shrinking_Layer.pdi"/>
  <File Type="PL-PDI-FILE" Name="Shrinking_Layer_pld.pdi"/>
  <File Type="RCFI_FILE" Name="Shrinking_Layer.rcfi"/>
  <File Type="CFI_FILE" Name="Shrinking_Layer.cfi"/>
  <File Type="RNPI_FILE" Name="Shrinking_Layer.rnpi"/>
  <File Type="ROUTE-RQS" Name="Shrinking_Layer_routed.rqs"/>
  <File Type="POSTROUTE-PHYSOPT-RQS" Name="Shrinking_Layer_postroute_physopted.rqs"/>
  <File Type="ROUTE-RQS-RPT" Name="route_report_qor_suggestions_0.rpt"/>
  <File Type="POSTROUTE-PHYSOPT-RQS-RPT" Name="postroute_physopt_report_qor_suggestions_0.rpt"/>
  <FileSet Name="sources" Type="DesignSrcs" RelSrcDir="$PSRCDIR/sources_1" RelGenDir="$PGENDIR/sources_1">
    <Filter Type="Srcs"/>
    <File Path="$PSRCDIR/sources_1/imports/new/AXIS_REGISTER.v">
      <FileInfo>
        <Attr Name="ImportPath" Val="$PPRDIR/../RGB2YCbCr_Converter/RGB2YCbCr_Converter.srcs/sources_1/imports/sources_1/new/AXIS_REGISTER.v"/>
        <Attr Name="ImportTime" Val="1751782284"/>
        <Attr Name="UsedIn" Val="synthesis"/>
        <Attr Name="UsedIn" Val="implementation"/>
        <Attr Name="UsedIn" Val="simulation"/>
      </FileInfo>
    </File>
    <File Path="$PSRCDIR/sources_1/new/Adder_Tree.v">
      <FileInfo>
        <Attr Name="UsedIn" Val="synthesis"/>
        <Attr Name="UsedIn" Val="implementation"/>
        <Attr Name="UsedIn" Val="simulation"/>
      </FileInfo>
    </File>
    <File Path="$PSRCDIR/sources_1/new/Convolution.v">
      <FileInfo>
        <Attr Name="UsedIn" Val="synthesis"/>
        <Attr Name="UsedIn" Val="implementation"/>
        <Attr Name="UsedIn" Val="simulation"/>
      </FileInfo>
    </File>
    <File Path="$PSRCDIR/sources_1/new/Multiplier_DSP.v">
      <FileInfo>
        <Attr Name="UsedIn" Val="synthesis"/>
        <Attr Name="UsedIn" Val="implementation"/>
        <Attr Name="UsedIn" Val="simulation"/>
      </FileInfo>
    </File>
    <File Path="$PSRCDIR/sources_1/imports/FSRCNN/pipelined_multiplier_2stage.v">
      <FileInfo>
        <Attr Name="ImportPath" Val="$PPRDIR/../../pipelined_multiplier_2stage.v"/>
        <Attr Name="ImportTime" Val="1750426222"/>
        <Attr Name="UsedIn" Val="synthesis"/>
        <Attr Name="UsedIn" Val="implementation"/>
        <Attr Name="UsedIn" Val="simulation"/>
      </FileInfo>
    </File>
    <File Path="$PSRCDIR/sources_1/new/Shrinking_Layer.v">
      <FileInfo>
        <Attr Name="UsedIn" Val="synthesis"/>
        <Attr Name="UsedIn" Val="implementation"/>
        <Attr Name="UsedIn" Val="simulation"/>
      </FileInfo>
    </File>
    <File Path="$PPRDIR/component.xml">
      <FileInfo SFType="IPXACT"/>
    </File>
    <Config>
      <Option Name="DesignMode" Val="RTL"/>
      <Option Name="TopModule" Val="Shrinking_Layer"/>
      <Option Name="TopAutoSet" Val="TRUE"/>
    </Config>
  </FileSet>
  <FileSet Name="constrs_in" Type="Constrs" RelSrcDir="$PSRCDIR/constrs_1" RelGenDir="$PGENDIR/constrs_1">
    <Filter Type="Constrs"/>
    <File Path="$PSRCDIR/constrs_1/imports/constraints_file/zcu102.xdc">
      <FileInfo>
        <Attr Name="ImportPath" Val="$PPRDIR/../../constraints_file/zcu102.xdc"/>
        <Attr Name="ImportTime" Val="1751779165"/>
        <Attr Name="UsedIn" Val="synthesis"/>
        <Attr Name="UsedIn" Val="implementation"/>
      </FileInfo>
    </File>
    <Config>
      <Option Name="ConstrsType" Val="XDC"/>
    </Config>
  </FileSet>
  <FileSet Name="utils" Type="Utils" RelSrcDir="$PSRCDIR/utils_1" RelGenDir="$PGENDIR/utils_1">
    <Filter Type="Utils"/>
    <File Path="$PSRCDIR/utils_1/imports/synth_1/Convolution.dcp">
      <FileInfo>
        <Attr Name="UsedIn" Val="synthesis"/>
        <Attr Name="UsedIn" Val="implementation"/>
        <Attr Name="UsedInSteps" Val="synth_1"/>
        <Attr Name="AutoDcp" Val="1"/>
      </FileInfo>
    </File>
    <Config>
      <Option Name="TopAutoSet" Val="TRUE"/>
    </Config>
  </FileSet>
  <Strategy Version="1" Minor="2">
    <StratHandle Name="Vivado Implementation Defaults" Flow="Vivado Implementation 2023"/>
    <Step Id="init_design"/>
    <Step Id="opt_design"/>
    <Step Id="power_opt_design"/>
    <Step Id="place_design"/>
    <Step Id="post_place_power_opt_design"/>
    <Step Id="phys_opt_design"/>
    <Step Id="route_design"/>
    <Step Id="post_route_phys_opt_design"/>
    <Step Id="write_bitstream"/>
    <Step Id="write_device_image"/>
  </Strategy>
  <BlockFileSet Type="BlockSrcs" Name="fifo_generator_0"/>
</GenRun>
